accoutning_api_py/__init__.py
accoutning_api_py/api.py
accoutning_api_py-0.2.0.dist-info/METADATA
accoutning_api_py-0.2.0.dist-info/WHEEL
accoutning_api_py-0.2.0.dist-info/RECORD
