Metadata-Version: 2.1
Name: accoutning-api-py
Version: 0.2.0
Summary: 
Author: Vincenzo Palazzo
Author-email: vincenzopalazzodev@gmail.com
Requires-Python: >=3.11,<4.0
Classifier: Programming Language :: Python :: 3
Classifier: Programming Language :: Python :: 3.11
Requires-Dist: requests (>=2.27.1,<3.0.0)
